{
  "part": "史部二十四",
  "outline": "地理類一\n",
  "name": "河南通志 八十卷\n",
  "source": "通行本\n",
  "source_url": "http://kanji.zinbun.kyoto-u.ac.jp/db-machine/ShikoTeiyo/0148302.html",
  "content": "國朝總督河南山東軍務兵部右侍郞王士俊等監修。河南之名。宋代惟屬洛陽一郡。故宋敏求作河南志。僅記西都典故。而不及他州。自明初設河南布政司。所屬八府。實跨河以北。封疆於古稍殊。故郡邑雖各有偏記。而未有統爲一書者。嘉靖中始創爲之。亦僅具崖略而已。徵引未能賅洽。考證亦未能精確。國朝順治十八年。復加續修。條理粗備。黃之雋謂康熙中嘗頒諸天下以爲式。後閱六七十年。未經修葺。郡邑分併。與新制多不相合。雍正九年。河東總督田文鏡。承命排纂。乃延編修孫灝。進士顧棟高等。開局蒐討。文鏡歿後。王士俊代爲總督。乃成書表上。考古證今。體例頗爲整密。惟書成之後。陳許二州。陞爲府。鄭州改隸開封。盧氏改隸陝州。南召復立縣治。因刊版已竣。皆未及增改云。\n"
}