{
  "part": "集部五",
  "outline": "別集類五\n",
  "name": "咸平集 三十卷\n",
  "source": "兩江總督採進本\n",
  "source_url": "http://kanji.zinbun.kyoto-u.ac.jp/db-machine/ShikoTeiyo/0318302.html",
  "content": "宋田錫撰。錫有奏議。已著錄。考奏議乃明安磐所輯。其文已全載此集中。然宋史藝文志。載錫奏議二卷。文獻通考。載錫咸平集五十卷。此本載奏議一卷。書三卷。賦五卷。論三卷。箴銘二卷。詩六卷。頌策笏記表狀七卷。制誥考詞三卷。以奏議與詩文集合爲一編。僅三十卷。則亦後人重輯之本。非其舊也。錫常慕魏徵李絳之爲人。以獻納爲己任。國老談苑記。太宗幸龍圖閣閱書。指西北架一漆畫篋。上親自署鑰者。謂學士陳堯叟曰。此田錫之奏疏也。愴然者久之。則當時已重其言。故其沒也。范仲淹作墓誌。司馬光作神道碑。而蘇軾序其奏議。亦比之賈誼。爲之操筆者。皆天下偉人。則錫之生平可知也。詩文乃其餘事。然亦具有典型。其氣體光明磊落。如其爲人。固終非淟涊者所得彷佛焉。\n"
}